benchmark/__init__.py
chatz/__init__.py
examples/__init__.py
test/__init__.py
chatz-0.0.0.dist-info/LICENSE
chatz-0.0.0.dist-info/METADATA
chatz-0.0.0.dist-info/WHEEL
chatz-0.0.0.dist-info/top_level.txt
chatz-0.0.0.dist-info/RECORD
